azure_ad_verify_token/__init__.py
azure_ad_verify_token/crypto.py
azure_ad_verify_token/verify.py
azure_ad_verify_token-0.4.0.dist-info/LICENSE.md
azure_ad_verify_token-0.4.0.dist-info/METADATA
azure_ad_verify_token-0.4.0.dist-info/WHEEL
azure_ad_verify_token-0.4.0.dist-info/top_level.txt
azure_ad_verify_token-0.4.0.dist-info/RECORD
