Metadata-Version: 2.1
Name: azure-ad-verify-token
Version: 0.4.0
Summary: Verify JWT issued by Azure Active Directory B2C in Python.
Home-page: https://github.com/odwyersoftware/azure-ad-verify-token
Author: O'Dwyer Software
Author-email: github@odwyer.software
License: Creative Commons Attribution-NonCommercial-NoDerivatives 4.0 International License
Classifier: Intended Audience :: Developers
Classifier: Operating System :: OS Independent
Classifier: Programming Language :: Python
Classifier: Programming Language :: Python :: 3
Classifier: Topic :: Internet :: WWW/HTTP
License-File: LICENSE.md
Requires-Dist: requests (<3.0.0,>=2.0.0)
Requires-Dist: cryptography (>=2.0.0)
Requires-Dist: pyjwt (<3.0.0,>=2.0.0)
